{"root":{"tags":null,"renderToIntermediateTexture":false,"maxLayoutCycle":3,"adaptHeightToChildren":false,"adaptWidthToChildren":false,"background":"","metadata":{"_previousCenter":{"x":1,"y":1}},"isHitTestVisible":true,"isPointerBlocker":false,"isFocusInvisible":false,"clipChildren":true,"clipContent":true,"useBitmapCache":false,"shadowOffsetX":0,"shadowOffsetY":0,"shadowBlur":0,"shadowColor":"black","hoverCursor":"","alpha":1,"scaleX":1,"scaleY":1,"rotation":0,"transformCenterY":0.5,"transformCenterX":0.5,"horizontalAlignment":2,"verticalAlignment":2,"fixedRatio":0,"width":"100%","height":"100%","color":"","zIndex":0,"notRenderable":false,"isVisible":true,"descendantsOnlyPadding":false,"paddingLeft":"0px","paddingRight":"0px","paddingTop":"0px","paddingBottom":"0px","left":"0px","top":"0px","linkOffsetX":"0px","linkOffsetY":"0px","isEnabled":true,"disabledColor":"#9a9a9a","disabledColorItem":"#6a6a6a","name":"root","className":"Container","children":[{"tags":["2:0","1:0","0:0"],"renderToIntermediateTexture":false,"maxLayoutCycle":3,"adaptHeightToChildren":false,"adaptWidthToChildren":false,"background":"","isHitTestVisible":true,"isPointerBlocker":true,"isFocusInvisible":false,"clipChildren":true,"clipContent":true,"useBitmapCache":false,"shadowOffsetX":0,"shadowOffsetY":0,"shadowBlur":0,"shadowColor":"black","hoverCursor":"","alpha":1,"scaleX":1,"scaleY":1,"rotation":0,"transformCenterY":0.5,"transformCenterX":0.5,"horizontalAlignment":2,"verticalAlignment":1,"fixedRatio":0,"width":"100%","height":"100%","color":"","zIndex":0,"notRenderable":false,"isVisible":true,"descendantsOnlyPadding":false,"paddingLeft":"0px","paddingRight":"0px","paddingTop":"0px","paddingBottom":"0px","left":"0px","top":"1.6558910227300316px","linkOffsetX":"0px","linkOffsetY":"0px","isEnabled":true,"disabledColor":"#9a9a9a","disabledColorItem":"#6a6a6a","name":"mainGrid","className":"Grid","children":[{"tags":null,"thickness":1,"cornerRadius":10,"renderToIntermediateTexture":false,"maxLayoutCycle":3,"adaptHeightToChildren":false,"adaptWidthToChildren":false,"background":"#C97B04FF","isHitTestVisible":true,"isPointerBlocker":true,"isFocusInvisible":false,"clipChildren":true,"clipContent":true,"useBitmapCache":false,"shadowOffsetX":0,"shadowOffsetY":0,"shadowBlur":0,"shadowColor":"black","hoverCursor":"","fontOffset":{"ascent":45,"height":57,"descent":12},"alpha":1,"scaleX":1,"scaleY":1,"rotation":0,"transformCenterY":0.5,"transformCenterX":0.5,"horizontalAlignment":1,"verticalAlignment":2,"fixedRatio":0,"width":"400px","height":"100px","color":"#ffffff","zIndex":0,"notRenderable":false,"isVisible":true,"descendantsOnlyPadding":false,"paddingLeft":"-200px","paddingRight":"200px","paddingTop":"0px","paddingBottom":"0px","left":"0px","top":"0px","linkOffsetX":"0px","linkOffsetY":"0px","isEnabled":true,"disabledColor":"#9a9a9a","disabledColorItem":"#6a6a6a","name":"returnButton","className":"Button","fontFamily":"Arial","fontSize":"50px","fontWeight":"","fontStyle":"","children":[{"tags":null,"resizeToFit":true,"textWrapping":1,"text":"Return","textHorizontalAlignment":2,"textVerticalAlignment":2,"lineSpacing":"0px","outlineWidth":1,"underline":false,"lineThrough":false,"outlineColor":"white","isHitTestVisible":true,"isPointerBlocker":false,"isFocusInvisible":false,"clipChildren":true,"clipContent":true,"useBitmapCache":false,"shadowOffsetX":0,"shadowOffsetY":0,"shadowBlur":0,"shadowColor":"black","hoverCursor":"","fontOffset":{"ascent":45,"height":57,"descent":12},"alpha":1,"scaleX":1,"scaleY":1,"rotation":0,"transformCenterY":0.5,"transformCenterX":0.5,"horizontalAlignment":2,"verticalAlignment":2,"fixedRatio":0,"width":"100%","height":"57px","color":"","zIndex":0,"notRenderable":false,"isVisible":true,"descendantsOnlyPadding":false,"paddingLeft":"0px","paddingRight":"0px","paddingTop":"0px","paddingBottom":"0px","left":"0px","top":"0px","linkOffsetX":"0px","linkOffsetY":"0px","isEnabled":true,"disabledColor":"#9a9a9a","disabledColorItem":"#6a6a6a","name":"textReturn","className":"TextBlock","fontFamily":"Arial","fontSize":"50px","fontWeight":"Bold","fontStyle":""}],"textBlockName":"textReturn"},{"tags":["2:0","1:1","1:0","0:1","0:0"],"renderToIntermediateTexture":false,"maxLayoutCycle":3,"adaptHeightToChildren":false,"adaptWidthToChildren":false,"background":"#00000000","isHitTestVisible":true,"isPointerBlocker":true,"isFocusInvisible":false,"clipChildren":true,"clipContent":true,"useBitmapCache":false,"shadowOffsetX":0,"shadowOffsetY":0,"shadowBlur":0,"shadowColor":"black","hoverCursor":"","alpha":1,"scaleX":1,"scaleY":1,"rotation":0,"transformCenterY":0.5,"transformCenterX":0.5,"horizontalAlignment":2,"verticalAlignment":2,"fixedRatio":0,"width":"100%","height":"100%","color":"","zIndex":0,"notRenderable":false,"isVisible":true,"descendantsOnlyPadding":false,"paddingLeft":"0px","paddingRight":"0px","paddingTop":"0px","paddingBottom":"0px","left":"0px","top":"0px","linkOffsetX":"0px","linkOffsetY":"0px","isEnabled":true,"disabledColor":"#9a9a9a","disabledColorItem":"#6a6a6a","name":"gridLevels","className":"Grid","children":[{"tags":null,"thickness":1,"cornerRadius":10,"renderToIntermediateTexture":false,"maxLayoutCycle":3,"adaptHeightToChildren":false,"adaptWidthToChildren":false,"background":"#333333","isHitTestVisible":true,"isPointerBlocker":true,"isFocusInvisible":false,"clipChildren":true,"clipContent":true,"useBitmapCache":false,"shadowOffsetX":0,"shadowOffsetY":0,"shadowBlur":0,"shadowColor":"black","hoverCursor":"","alpha":1,"scaleX":1,"scaleY":1,"rotation":0,"transformCenterY":0.5,"transformCenterX":0.5,"horizontalAlignment":2,"verticalAlignment":0,"fixedRatio":0,"width":"600px","height":"130px","color":"#ffffff","zIndex":0,"notRenderable":false,"isVisible":true,"descendantsOnlyPadding":false,"paddingLeft":"0px","paddingRight":"0px","paddingTop":"0px","paddingBottom":"0px","left":"50px","top":"0px","linkOffsetX":"0px","linkOffsetY":"0px","isEnabled":true,"disabledColor":"#9a9a9a","disabledColorItem":"#6a6a6a","name":"buttonLevel5","className":"Button","children":[{"tags":["0:1","0:0"],"renderToIntermediateTexture":false,"maxLayoutCycle":3,"adaptHeightToChildren":false,"adaptWidthToChildren":false,"background":"#C97B04FF","isHitTestVisible":true,"isPointerBlocker":true,"isFocusInvisible":false,"clipChildren":true,"clipContent":true,"useBitmapCache":false,"shadowOffsetX":10,"shadowOffsetY":10,"shadowBlur":0,"shadowColor":"black","hoverCursor":"","alpha":1,"scaleX":1,"scaleY":1,"rotation":0,"transformCenterY":0.5,"transformCenterX":0.5,"horizontalAlignment":2,"verticalAlignment":2,"fixedRatio":0,"width":"100%","height":"100%","color":"#000000FF","zIndex":0,"notRenderable":false,"isVisible":true,"descendantsOnlyPadding":false,"paddingLeft":"0px","paddingRight":"0px","paddingTop":"0px","paddingBottom":"0px","left":"0px","top":"0px","linkOffsetX":"0px","linkOffsetY":"0px","isEnabled":true,"disabledColor":"#9a9a9a","disabledColorItem":"#6a6a6a","name":"gridLevel5","className":"Grid","children":[{"tags":null,"resizeToFit":false,"textWrapping":0,"text":"Level 5 ","textHorizontalAlignment":0,"textVerticalAlignment":2,"lineSpacing":"0px","outlineWidth":0,"underline":false,"lineThrough":false,"outlineColor":"white","isHitTestVisible":true,"isPointerBlocker":true,"isFocusInvisible":false,"clipChildren":true,"clipContent":true,"useBitmapCache":false,"shadowOffsetX":0,"shadowOffsetY":0,"shadowBlur":0,"shadowColor":"black","hoverCursor":"","fontOffset":{"ascent":45,"height":57,"descent":12},"alpha":1,"scaleX":1,"scaleY":1,"rotation":0,"transformCenterY":0.5,"transformCenterX":0.5,"horizontalAlignment":0,"verticalAlignment":2,"fixedRatio":0,"width":"100%","height":"100%","color":"#FFFFFFFF","zIndex":0,"notRenderable":false,"isVisible":true,"descendantsOnlyPadding":false,"paddingLeft":"0px","paddingRight":"0px","paddingTop":"0px","paddingBottom":"0px","left":"0px","top":"0px","linkOffsetX":"0px","linkOffsetY":"0px","isEnabled":true,"disabledColor":"#9a9a9a","disabledColorItem":"#6a6a6a","name":"nameLevel5","className":"TextBlock","fontFamily":"Arial","fontSize":"50px","fontWeight":"Bold","fontStyle":""},{"tags":null,"resizeToFit":true,"textWrapping":0,"text":"5","textHorizontalAlignment":2,"textVerticalAlignment":2,"lineSpacing":"0px","outlineWidth":0,"underline":false,"lineThrough":false,"outlineColor":"white","isHitTestVisible":true,"isPointerBlocker":true,"isFocusInvisible":false,"clipChildren":true,"clipContent":true,"useBitmapCache":false,"shadowOffsetX":0,"shadowOffsetY":0,"shadowBlur":0,"shadowColor":"black","hoverCursor":"","fontOffset":{"ascent":45,"height":57,"descent":12},"alpha":1,"scaleX":1,"scaleY":1,"rotation":0,"transformCenterY":0.5,"transformCenterX":0.5,"horizontalAlignment":2,"verticalAlignment":2,"fixedRatio":0,"width":"28px","height":"57px","color":"#FFFFFFFF","zIndex":0,"notRenderable":false,"isVisible":true,"descendantsOnlyPadding":false,"paddingLeft":"0px","paddingRight":"0px","paddingTop":"0px","paddingBottom":"0px","left":"0px","top":"0px","linkOffsetX":"0px","linkOffsetY":"0px","isEnabled":true,"disabledColor":"#9a9a9a","disabledColorItem":"#6a6a6a","name":"numLevel5","className":"TextBlock","fontFamily":"Arial","fontSize":"50px","fontWeight":"Bold","fontStyle":""}],"columnCount":3,"rowCount":1,"columns":[{"value":0.15,"unit":0},{"value":0.65,"unit":0},{"value":0.2,"unit":0}],"rows":[{"value":1,"unit":0}]}]},{"tags":null,"thickness":1,"cornerRadius":10,"renderToIntermediateTexture":false,"maxLayoutCycle":3,"adaptHeightToChildren":false,"adaptWidthToChildren":false,"background":"#333333","isHitTestVisible":true,"isPointerBlocker":true,"isFocusInvisible":false,"clipChildren":true,"clipContent":true,"useBitmapCache":false,"shadowOffsetX":0,"shadowOffsetY":0,"shadowBlur":0,"shadowColor":"black","hoverCursor":"","alpha":1,"scaleX":1,"scaleY":1,"rotation":0,"transformCenterY":0.5,"transformCenterX":0.5,"horizontalAlignment":2,"verticalAlignment":2,"fixedRatio":0,"width":"600px","height":"130px","color":"#ffffff","zIndex":0,"notRenderable":false,"isVisible":true,"descendantsOnlyPadding":false,"paddingLeft":"0px","paddingRight":"0px","paddingTop":"0px","paddingBottom":"0px","left":"-50px","top":"0px","linkOffsetX":"0px","linkOffsetY":"0px","isEnabled":true,"disabledColor":"#9a9a9a","disabledColorItem":"#6a6a6a","name":"buttonLevel4","className":"Button","children":[{"tags":["0:1","0:0"],"renderToIntermediateTexture":false,"maxLayoutCycle":3,"adaptHeightToChildren":false,"adaptWidthToChildren":false,"background":"#C97B04FF","isHitTestVisible":true,"isPointerBlocker":true,"isFocusInvisible":false,"clipChildren":true,"clipContent":true,"useBitmapCache":false,"shadowOffsetX":10,"shadowOffsetY":10,"shadowBlur":0,"shadowColor":"black","hoverCursor":"","alpha":1,"scaleX":1,"scaleY":1,"rotation":0,"transformCenterY":0.5,"transformCenterX":0.5,"horizontalAlignment":2,"verticalAlignment":2,"fixedRatio":0,"width":"100%","height":"100%","color":"#000000FF","zIndex":0,"notRenderable":false,"isVisible":true,"descendantsOnlyPadding":false,"paddingLeft":"0px","paddingRight":"0px","paddingTop":"0px","paddingBottom":"0px","left":"0px","top":"0px","linkOffsetX":"0px","linkOffsetY":"0px","isEnabled":true,"disabledColor":"#9a9a9a","disabledColorItem":"#6a6a6a","name":"gridLevel4","className":"Grid","children":[{"tags":null,"resizeToFit":true,"textWrapping":0,"text":"Level 4","textHorizontalAlignment":2,"textVerticalAlignment":2,"lineSpacing":"0px","outlineWidth":0,"underline":false,"lineThrough":false,"outlineColor":"white","isHitTestVisible":true,"isPointerBlocker":true,"isFocusInvisible":false,"clipChildren":true,"clipContent":true,"useBitmapCache":false,"shadowOffsetX":0,"shadowOffsetY":0,"shadowBlur":0,"shadowColor":"black","hoverCursor":"","fontOffset":{"ascent":45,"height":57,"descent":12},"alpha":1,"scaleX":1,"scaleY":1,"rotation":0,"transformCenterY":0.5,"transformCenterX":0.5,"horizontalAlignment":0,"verticalAlignment":2,"fixedRatio":0,"width":"172px","height":"57px","color":"#FFFFFFFF","zIndex":0,"notRenderable":false,"isVisible":true,"descendantsOnlyPadding":false,"paddingLeft":"0px","paddingRight":"0px","paddingTop":"0px","paddingBottom":"0px","left":"0px","top":"0px","linkOffsetX":"0px","linkOffsetY":"0px","isEnabled":true,"disabledColor":"#9a9a9a","disabledColorItem":"#6a6a6a","name":"nameLevel4","className":"TextBlock","fontFamily":"Arial","fontSize":"50px","fontWeight":"Bold","fontStyle":""},{"tags":null,"resizeToFit":true,"textWrapping":0,"text":"4","textHorizontalAlignment":2,"textVerticalAlignment":2,"lineSpacing":"0px","outlineWidth":0,"underline":false,"lineThrough":false,"outlineColor":"white","isHitTestVisible":true,"isPointerBlocker":true,"isFocusInvisible":false,"clipChildren":true,"clipContent":true,"useBitmapCache":false,"shadowOffsetX":0,"shadowOffsetY":0,"shadowBlur":0,"shadowColor":"black","hoverCursor":"","fontOffset":{"ascent":45,"height":57,"descent":12},"alpha":1,"scaleX":1,"scaleY":1,"rotation":0,"transformCenterY":0.5,"transformCenterX":0.5,"horizontalAlignment":2,"verticalAlignment":2,"fixedRatio":0,"width":"27px","height":"57px","color":"#FFFFFFFF","zIndex":0,"notRenderable":false,"isVisible":true,"descendantsOnlyPadding":false,"paddingLeft":"0px","paddingRight":"0px","paddingTop":"0px","paddingBottom":"0px","left":"0px","top":"0px","linkOffsetX":"0px","linkOffsetY":"0px","isEnabled":true,"disabledColor":"#9a9a9a","disabledColorItem":"#6a6a6a","name":"numLevel4","className":"TextBlock","fontFamily":"Arial","fontSize":"50px","fontWeight":"Bold","fontStyle":""}],"columnCount":3,"rowCount":1,"columns":[{"value":0.15,"unit":0},{"value":0.65,"unit":0},{"value":0.2,"unit":0}],"rows":[{"value":1,"unit":0}]}]},{"tags":null,"thickness":1,"cornerRadius":10,"renderToIntermediateTexture":false,"maxLayoutCycle":3,"adaptHeightToChildren":false,"adaptWidthToChildren":false,"background":"#333333","isHitTestVisible":true,"isPointerBlocker":true,"isFocusInvisible":false,"clipChildren":true,"clipContent":true,"useBitmapCache":false,"shadowOffsetX":0,"shadowOffsetY":0,"shadowBlur":0,"shadowColor":"black","hoverCursor":"","alpha":1,"scaleX":1,"scaleY":1,"rotation":0,"transformCenterY":0.5,"transformCenterX":0.5,"horizontalAlignment":2,"verticalAlignment":2,"fixedRatio":0,"width":"600px","height":"130px","color":"#FFFFFFFF","zIndex":0,"notRenderable":false,"isVisible":true,"descendantsOnlyPadding":false,"paddingLeft":"0px","paddingRight":"0px","paddingTop":"0px","paddingBottom":"0px","left":"50px","top":"0px","linkOffsetX":"0px","linkOffsetY":"0px","isEnabled":true,"disabledColor":"#9a9a9a","disabledColorItem":"#6a6a6a","name":"buttonLevel3","className":"Button","children":[{"tags":["0:1","0:0"],"renderToIntermediateTexture":false,"maxLayoutCycle":3,"adaptHeightToChildren":false,"adaptWidthToChildren":false,"background":"#C97B04FF","isHitTestVisible":true,"isPointerBlocker":true,"isFocusInvisible":false,"clipChildren":true,"clipContent":true,"useBitmapCache":false,"shadowOffsetX":10,"shadowOffsetY":10,"shadowBlur":0,"shadowColor":"black","hoverCursor":"","alpha":1,"scaleX":1,"scaleY":1,"rotation":0,"transformCenterY":0.5,"transformCenterX":0.5,"horizontalAlignment":2,"verticalAlignment":2,"fixedRatio":0,"width":"100%","height":"100%","color":"#000000FF","zIndex":0,"notRenderable":false,"isVisible":true,"descendantsOnlyPadding":false,"paddingLeft":"0px","paddingRight":"0px","paddingTop":"0px","paddingBottom":"0px","left":"0px","top":"0px","linkOffsetX":"0px","linkOffsetY":"0px","isEnabled":true,"disabledColor":"#9a9a9a","disabledColorItem":"#6a6a6a","name":"gridLevel3","className":"Grid","children":[{"tags":null,"resizeToFit":false,"textWrapping":1,"text":"Level 3","textHorizontalAlignment":0,"textVerticalAlignment":2,"lineSpacing":"0px","outlineWidth":0,"underline":false,"lineThrough":false,"outlineColor":"white","isHitTestVisible":true,"isPointerBlocker":false,"isFocusInvisible":false,"clipChildren":true,"clipContent":true,"useBitmapCache":false,"shadowOffsetX":0,"shadowOffsetY":0,"shadowBlur":0,"shadowColor":"#000000","hoverCursor":"","fontOffset":{"ascent":45,"height":57,"descent":12},"alpha":1,"scaleX":1,"scaleY":1,"rotation":0,"transformCenterY":0.5,"transformCenterX":0.5,"horizontalAlignment":2,"verticalAlignment":2,"fixedRatio":0,"width":"100%","height":"100%","color":"#FFFFFFFF","zIndex":0,"notRenderable":false,"isVisible":true,"descendantsOnlyPadding":false,"paddingLeft":"0px","paddingRight":"0px","paddingTop":"0px","paddingBottom":"0px","left":"0px","top":"0px","linkOffsetX":"0px","linkOffsetY":"0px","isEnabled":true,"disabledColor":"#9a9a9a","disabledColorItem":"#6a6a6a","name":"nameLevel3","className":"TextBlock","fontFamily":"Arial","fontSize":"50px","fontWeight":"Bold","fontStyle":""},{"tags":null,"resizeToFit":false,"textWrapping":0,"text":"3","textHorizontalAlignment":2,"textVerticalAlignment":2,"lineSpacing":"0px","outlineWidth":0,"underline":false,"lineThrough":false,"outlineColor":"white","isHitTestVisible":true,"isPointerBlocker":true,"isFocusInvisible":false,"clipChildren":true,"clipContent":true,"useBitmapCache":false,"shadowOffsetX":0,"shadowOffsetY":0,"shadowBlur":0,"shadowColor":"black","hoverCursor":"","fontOffset":{"ascent":45,"height":57,"descent":12},"alpha":1,"scaleX":1,"scaleY":1,"rotation":0,"transformCenterY":0.5,"transformCenterX":0.5,"horizontalAlignment":2,"verticalAlignment":2,"fixedRatio":0,"width":"100%","height":"100%","color":"#FFFFFFFF","zIndex":0,"notRenderable":false,"isVisible":true,"descendantsOnlyPadding":false,"paddingLeft":"0px","paddingRight":"0px","paddingTop":"0px","paddingBottom":"0px","left":"0px","top":"0px","linkOffsetX":"0px","linkOffsetY":"0px","isEnabled":true,"disabledColor":"#9a9a9a","disabledColorItem":"#6a6a6a","name":"numLevel3","className":"TextBlock","fontFamily":"Arial","fontSize":"50px","fontWeight":"Bold","fontStyle":""}],"columnCount":3,"rowCount":1,"columns":[{"value":0.15,"unit":0},{"value":0.65,"unit":0},{"value":0.2,"unit":0}],"rows":[{"value":1,"unit":0}]}]},{"tags":null,"thickness":1,"cornerRadius":10,"renderToIntermediateTexture":false,"maxLayoutCycle":3,"adaptHeightToChildren":false,"adaptWidthToChildren":false,"background":"#333333","isHitTestVisible":true,"isPointerBlocker":true,"isFocusInvisible":false,"clipChildren":true,"clipContent":true,"useBitmapCache":false,"shadowOffsetX":0,"shadowOffsetY":0,"shadowBlur":0,"shadowColor":"black","hoverCursor":"","alpha":1,"scaleX":1,"scaleY":1,"rotation":0,"transformCenterY":0.5,"transformCenterX":0.5,"horizontalAlignment":2,"verticalAlignment":1,"fixedRatio":0,"width":"600px","height":"130px","color":"#FFFFFFFF","zIndex":0,"notRenderable":false,"isVisible":true,"descendantsOnlyPadding":false,"paddingLeft":"0px","paddingRight":"0px","paddingTop":"0px","paddingBottom":"0px","left":"-50px","top":"0px","linkOffsetX":"0px","linkOffsetY":"0px","isEnabled":true,"disabledColor":"#9a9a9a","disabledColorItem":"#6a6a6a","name":"buttonLevel2","className":"Button","children":[{"tags":["0:1","0:0"],"renderToIntermediateTexture":false,"maxLayoutCycle":3,"adaptHeightToChildren":false,"adaptWidthToChildren":false,"background":"#C97B04FF","isHitTestVisible":true,"isPointerBlocker":true,"isFocusInvisible":false,"clipChildren":true,"clipContent":true,"useBitmapCache":false,"shadowOffsetX":10,"shadowOffsetY":10,"shadowBlur":0,"shadowColor":"black","hoverCursor":"","alpha":1,"scaleX":1,"scaleY":1,"rotation":0,"transformCenterY":0.5,"transformCenterX":0.5,"horizontalAlignment":2,"verticalAlignment":2,"fixedRatio":0,"width":"100%","height":"100%","color":"#000000FF","zIndex":0,"notRenderable":false,"isVisible":true,"descendantsOnlyPadding":false,"paddingLeft":"0px","paddingRight":"0px","paddingTop":"0px","paddingBottom":"0px","left":"0px","top":"0px","linkOffsetX":"0px","linkOffsetY":"0px","isEnabled":true,"disabledColor":"#9a9a9a","disabledColorItem":"#6a6a6a","name":"gridLevel2","className":"Grid","children":[{"tags":null,"resizeToFit":true,"textWrapping":0,"text":"The following","textHorizontalAlignment":2,"textVerticalAlignment":2,"lineSpacing":"0px","outlineWidth":0,"underline":false,"lineThrough":false,"outlineColor":"white","isHitTestVisible":true,"isPointerBlocker":true,"isFocusInvisible":false,"clipChildren":true,"clipContent":true,"useBitmapCache":false,"shadowOffsetX":0,"shadowOffsetY":0,"shadowBlur":0,"shadowColor":"black","hoverCursor":"","fontOffset":{"ascent":45,"height":57,"descent":12},"alpha":1,"scaleX":1,"scaleY":1,"rotation":0,"transformCenterY":0.5,"transformCenterX":0.5,"horizontalAlignment":0,"verticalAlignment":2,"fixedRatio":0,"width":"320px","height":"57px","color":"#FFFFFFFF","zIndex":0,"notRenderable":false,"isVisible":true,"descendantsOnlyPadding":false,"paddingLeft":"0px","paddingRight":"0px","paddingTop":"0px","paddingBottom":"0px","left":"0px","top":"0px","linkOffsetX":"0px","linkOffsetY":"0px","isEnabled":true,"disabledColor":"#9a9a9a","disabledColorItem":"#6a6a6a","name":"nameLevel2","className":"TextBlock","fontFamily":"Arial","fontSize":"50px","fontWeight":"Bold","fontStyle":""},{"tags":null,"resizeToFit":true,"textWrapping":0,"text":"2","textHorizontalAlignment":2,"textVerticalAlignment":2,"lineSpacing":"0px","outlineWidth":0,"underline":false,"lineThrough":false,"outlineColor":"white","isHitTestVisible":true,"isPointerBlocker":true,"isFocusInvisible":false,"clipChildren":true,"clipContent":true,"useBitmapCache":false,"shadowOffsetX":0,"shadowOffsetY":0,"shadowBlur":0,"shadowColor":"black","hoverCursor":"","fontOffset":{"ascent":45,"height":57,"descent":12},"alpha":1,"scaleX":1,"scaleY":1,"rotation":0,"transformCenterY":0.5,"transformCenterX":0.5,"horizontalAlignment":2,"verticalAlignment":2,"fixedRatio":0,"width":"26px","height":"57px","color":"#FFFFFFFF","zIndex":0,"notRenderable":false,"isVisible":true,"descendantsOnlyPadding":false,"paddingLeft":"0px","paddingRight":"0px","paddingTop":"0px","paddingBottom":"0px","left":"0px","top":"0px","linkOffsetX":"0px","linkOffsetY":"0px","isEnabled":true,"disabledColor":"#9a9a9a","disabledColorItem":"#6a6a6a","name":"numLevel2","className":"TextBlock","fontFamily":"Arial","fontSize":"50px","fontWeight":"Bold","fontStyle":""}],"columnCount":3,"rowCount":1,"columns":[{"value":0.15,"unit":0},{"value":0.65,"unit":0},{"value":0.2,"unit":0}],"rows":[{"value":1,"unit":0}]}]},{"tags":null,"thickness":1,"cornerRadius":10,"renderToIntermediateTexture":false,"maxLayoutCycle":3,"adaptHeightToChildren":false,"adaptWidthToChildren":false,"background":"#333333","isHitTestVisible":true,"isPointerBlocker":true,"isFocusInvisible":false,"clipChildren":true,"clipContent":true,"useBitmapCache":false,"shadowOffsetX":0,"shadowOffsetY":0,"shadowBlur":0,"shadowColor":"black","hoverCursor":"","alpha":1,"scaleX":1,"scaleY":1,"rotation":0,"transformCenterY":0.5,"transformCenterX":0.5,"horizontalAlignment":2,"verticalAlignment":1,"fixedRatio":0,"width":"600px","height":"130px","color":"#FFFFFFFF","zIndex":0,"notRenderable":false,"isVisible":true,"descendantsOnlyPadding":false,"paddingLeft":"0px","paddingRight":"0px","paddingTop":"0px","paddingBottom":"0px","left":"50px","top":"0px","linkOffsetX":"0px","linkOffsetY":"0px","isEnabled":true,"disabledColor":"#9a9a9a","disabledColorItem":"#6a6a6a","name":"buttonLevel1","className":"Button","children":[{"tags":["0:1","0:0"],"renderToIntermediateTexture":false,"maxLayoutCycle":3,"adaptHeightToChildren":false,"adaptWidthToChildren":false,"background":"#C97B04FF","isHitTestVisible":true,"isPointerBlocker":true,"isFocusInvisible":false,"clipChildren":true,"clipContent":true,"useBitmapCache":false,"shadowOffsetX":10,"shadowOffsetY":10,"shadowBlur":0,"shadowColor":"black","hoverCursor":"","alpha":1,"scaleX":1,"scaleY":1,"rotation":0,"transformCenterY":0.5,"transformCenterX":0.5,"horizontalAlignment":2,"verticalAlignment":1,"fixedRatio":0,"width":"100%","height":"100%","color":"#000000FF","zIndex":0,"notRenderable":false,"isVisible":true,"descendantsOnlyPadding":false,"paddingLeft":"0px","paddingRight":"0px","paddingTop":"0px","paddingBottom":"0px","left":"0px","top":"0px","linkOffsetX":"0px","linkOffsetY":"0px","isEnabled":true,"disabledColor":"#9a9a9a","disabledColorItem":"#6a6a6a","name":"gridLevel1","className":"Grid","children":[{"tags":null,"resizeToFit":true,"textWrapping":0,"text":"The beginning","textHorizontalAlignment":2,"textVerticalAlignment":2,"lineSpacing":"0px","outlineWidth":0,"underline":false,"lineThrough":false,"outlineColor":"white","isHitTestVisible":true,"isPointerBlocker":true,"isFocusInvisible":false,"clipChildren":true,"clipContent":true,"useBitmapCache":false,"shadowOffsetX":0,"shadowOffsetY":0,"shadowBlur":0,"shadowColor":"black","hoverCursor":"","fontOffset":{"ascent":45,"height":57,"descent":12},"alpha":1,"scaleX":1,"scaleY":1,"rotation":0,"transformCenterY":0.5,"transformCenterX":0.5,"horizontalAlignment":0,"verticalAlignment":2,"fixedRatio":0,"width":"339px","height":"57px","color":"#FFFFFFFF","zIndex":0,"notRenderable":false,"isVisible":true,"descendantsOnlyPadding":false,"paddingLeft":"0px","paddingRight":"0px","paddingTop":"0px","paddingBottom":"0px","left":"0px","top":"0px","linkOffsetX":"0px","linkOffsetY":"0px","isEnabled":true,"disabledColor":"#9a9a9a","disabledColorItem":"#6a6a6a","name":"nameLevel1","className":"TextBlock","fontFamily":"Arial","fontSize":"50px","fontWeight":"Bold","fontStyle":""},{"tags":null,"resizeToFit":true,"textWrapping":1,"text":"1","textHorizontalAlignment":2,"textVerticalAlignment":2,"lineSpacing":"0px","outlineWidth":0,"underline":false,"lineThrough":false,"outlineColor":"white","isHitTestVisible":true,"isPointerBlocker":true,"isFocusInvisible":false,"clipChildren":true,"clipContent":true,"useBitmapCache":false,"shadowOffsetX":0,"shadowOffsetY":0,"shadowBlur":0,"shadowColor":"black","hoverCursor":"","fontOffset":{"ascent":45,"height":57,"descent":12},"alpha":1,"scaleX":1,"scaleY":1,"rotation":0,"transformCenterY":0.5,"transformCenterX":0.5,"horizontalAlignment":2,"verticalAlignment":2,"fixedRatio":0,"width":"29px","height":"57px","color":"#FFFFFFFF","zIndex":0,"notRenderable":false,"isVisible":true,"descendantsOnlyPadding":false,"paddingLeft":"0px","paddingRight":"0px","paddingTop":"0px","paddingBottom":"0px","left":"0px","top":"0px","linkOffsetX":"0px","linkOffsetY":"0px","isEnabled":true,"disabledColor":"#9a9a9a","disabledColorItem":"#6a6a6a","name":"numLevel1","className":"TextBlock","fontFamily":"Arial","fontSize":"50px","fontWeight":"Bold","fontStyle":""}],"columnCount":3,"rowCount":1,"columns":[{"value":0.15,"unit":0},{"value":0.65,"unit":0},{"value":0.2,"unit":0}],"rows":[{"value":1,"unit":0}]}]}],"columnCount":2,"rowCount":3,"columns":[{"value":0.5,"unit":0},{"value":0.5,"unit":0}],"rows":[{"value":0.33333333333333337,"unit":0},{"value":0.33333333333333337,"unit":0},{"value":0.33333333333333337,"unit":0}]},{"tags":null,"resizeToFit":true,"textWrapping":1,"text":"Lost in Yourself","textHorizontalAlignment":2,"textVerticalAlignment":2,"lineSpacing":"0px","outlineWidth":0,"underline":false,"lineThrough":false,"outlineColor":"white","isHitTestVisible":true,"isPointerBlocker":true,"isFocusInvisible":false,"clipChildren":true,"clipContent":true,"useBitmapCache":false,"shadowOffsetX":0,"shadowOffsetY":0,"shadowBlur":0,"shadowColor":"black","hoverCursor":"","fontOffset":{"ascent":190,"height":238.5,"descent":48.5},"alpha":1,"scaleX":1,"scaleY":1,"rotation":0,"transformCenterY":0.5,"transformCenterX":0.5,"horizontalAlignment":2,"verticalAlignment":1,"fixedRatio":0,"width":"100%","height":"238px","color":"#FFFFFFFF","zIndex":0,"notRenderable":false,"isVisible":true,"descendantsOnlyPadding":false,"paddingLeft":"0px","paddingRight":"0px","paddingTop":"0px","paddingBottom":"0px","left":"0px","top":"0px","linkOffsetX":"0px","linkOffsetY":"0px","isEnabled":true,"disabledColor":"#9a9a9a","disabledColorItem":"#6a6a6a","name":"gameName","className":"TextBlock","fontFamily":"Arial","fontSize":"210px","fontWeight":"bold","fontStyle":""}],"columnCount":1,"rowCount":3,"columns":[{"value":1,"unit":0}],"rows":[{"value":0.30303030303030304,"unit":0},{"value":0.5151515151515151,"unit":0},{"value":0.18181818181818182,"unit":0}]}]},"width":1920,"height":1080}